LICENSE
README.md
setup.py
docums_table_reader_plugin/__init__.py
docums_table_reader_plugin/plugin.py
docums_table_reader_plugin/safe_eval.py
docums_table_reader_plugin.egg-info/PKG-INFO
docums_table_reader_plugin.egg-info/SOURCES.txt
docums_table_reader_plugin.egg-info/dependency_links.txt
docums_table_reader_plugin.egg-info/entry_points.txt
docums_table_reader_plugin.egg-info/requires.txt
docums_table_reader_plugin.egg-info/top_level.txt