Metadata-Version: 2.1
Name: docums-table-reader-plugin
Version: 1.0.0
Summary: Docums plugin to directly insert tables from files into markdown.
Home-page: https://github.com/khanhduy1407/docums-table-reader-plugin
Author: NKDuy
Author-email: kn145660@gmail.com
License: MIT
Keywords: docums plugin
Platform: UNKNOWN
Classifier: Operating System :: OS Independent
Classifier: Programming Language :: Python
Classifier: Programming Language :: Python :: 3
Classifier: Programming Language :: Python :: 3.7
Classifier: Programming Language :: Python :: 3.8
Classifier: Programming Language :: Python :: 3.9
Classifier: Programming Language :: Python :: 3.10
Classifier: License :: OSI Approved :: MIT License
Requires-Python: >=3.6
License-File: LICENSE
